{
  "Main": {
    "site_title": {
      "type": "StructuredText",
      "config": {
        "single": "heading1",
        "label": "Site Title",
        "placeholder": "Your Captivating Title"
      }
    },
    "site_url": {
      "type": "StructuredText",
      "config": {
        "single": "paragraph",
        "label": "Site URL",
        "placeholder": "https://www.example.com"
      }
    },
    "description": {
      "type": "StructuredText",
      "config": {
        "single": "paragraph",
        "label": "Description",
        "placeholder": "Default Description"
      }
    },
    "logo": {
      "type": "Image",
      "config": {
        "constraint": {},
        "thumbnails": [],
        "label": "Logo"
      }
    }
  },
  "Social": {
    "facebook": {
      "type": "Link",
      "config": {
        "label": "Facebook"
      }
    },
    "twitter": {
      "type": "Link",
      "config": {
        "label": "Twitter"
      }
    },
    "instagram": {
      "type": "Link",
      "config": {
        "label": "Instagram"
      }
    },
    "pinterest": {
      "type": "Link",
      "config": {
        "label": "Pinterest"
      }
    },
    "email": {
      "type": "Link",
      "config": {
        "label": "Email"
      }
    },
    "twitter_author": {
      "type": "StructuredText",
      "config": {
        "single": "paragraph",
        "label": "Twitter Author"
      }
    }
  },
  "Main Navigation": {
    "display_name": {
      "type": "StructuredText",
      "config": {
        "single": "heading1",
        "label": "Display name"
      }
    },
    "nav": {
      "type": "Slices",
      "fieldset": "Slice zone",
      "config": {
        "choices": {
          "nav_item": {
            "type": "Slice",
            "fieldset": "Nav Item",
            "description": "Nav Item with Sub Navigation",
            "icon": "insert_link",
            "non-repeat": {
              "label": {
                "type": "StructuredText",
                "config": {
                  "single": "paragraph",
                  "label": "Label",
                  "placeholder": "Enter Link Label..."
                }
              },
              "link": {
                "type": "Link",
                "config": {
                  "label": "Link",
                  "placeholder": "Select Link..."
                }
              }
            },
            "repeat": {
              "sub_nav_link_label": {
                "type": "StructuredText",
                "config": {
                  "single": "paragraph",
                  "label": "Sub Nav Link Label",
                  "placeholder": "Enter Sub Nav Link Label..."
                }
              },
              "sub_nav_link": {
                "type": "Link",
                "config": {
                  "label": "Sub Nav Link",
                  "placeholder": "Select Sub Nav Link..."
                }
              }
            }
          }
        }
      }
    }
  },
  "Contact": {
    "email1": {
      "type": "StructuredText",
      "config": {
        "single": "paragraph",
        "label": "Email"
      }
    },
    "phone": {
      "type": "StructuredText",
      "config": {
        "single": "paragraph",
        "label": "Phone"
      }
    },
    "fax": {
      "type": "StructuredText",
      "config": {
        "single": "paragraph",
        "label": "Fax"
      }
    },
    "contact_form_embed": {
      "type": "StructuredText",
      "config": {
        "multi": "preformatted",
        "label": "Contact Form Embed"
      }
    },
    "san_antonio_address": {
      "type": "StructuredText",
      "config": {
        "multi": "paragraph, preformatted, heading1, heading2, heading3, heading4, heading5, heading6, strong, em, hyperlink, image, embed, list-item, o-list-item, o-list-item",
        "label": "San Antonio Address"
      }
    },
    "san_antonia_map_embed": {
      "type": "StructuredText",
      "config": {
        "single": "preformatted",
        "label": "San Antonia Map Embed"
      }
    },
    "dallas_fort_worth_address": {
      "type": "StructuredText",
      "config": {
        "multi": "paragraph, preformatted, heading1, heading2, heading3, heading4, heading5, heading6, strong, em, hyperlink, image, embed, list-item, o-list-item, o-list-item",
        "label": "Dallas Fort Worth Address"
      }
    },
    "dalles_fort_worth_map_embed": {
      "type": "StructuredText",
      "config": {
        "single": "preformatted",
        "label": "Dalles Fort Worth Map Embed"
      }
    }
  }
}
